mcp_article_fetch/__init__.py
mcp_article_fetch/mcp_logger.py
mcp_article_fetch/server.py
mcp_article_fetch-0.1.8.dist-info/METADATA
mcp_article_fetch-0.1.8.dist-info/WHEEL
mcp_article_fetch-0.1.8.dist-info/entry_points.txt
mcp_article_fetch-0.1.8.dist-info/top_level.txt
mcp_article_fetch-0.1.8.dist-info/RECORD
